<ui:UiBinder xmlns:ui='urn:ui:com.google.gwt.uibinder'
             xmlns:g='urn:import:com.google.gwt.user.client.ui'
             xmlns:myWidgect='urn:import:com.myonlinebd.catalog.client.navigation'>


    <ui:with field='style' type='com.myonlinebd.catalog.client.resources.ImagesResources'/>

    <g:HTMLPanel>
        <myWidgect:HeaderView ui:field="header">

        </myWidgect:HeaderView>
        <div>
            <g:Image resource="{style.ok}"/>
        </div>
        <div>
            <p>Поздравления вие успешно създадохте акаунт</p>
        </div>

    </g:HTMLPanel>
</ui:UiBinder>